python_mathematics_exercises_generator/__init__.py
python_mathematics_exercises_generator/__main__.py
python_mathematics_exercises_generator/skeleton.py
python_mathematics_exercises_generator-0.0.1.dist-info/LICENSE.txt
python_mathematics_exercises_generator-0.0.1.dist-info/METADATA
python_mathematics_exercises_generator-0.0.1.dist-info/WHEEL
python_mathematics_exercises_generator-0.0.1.dist-info/entry_points.txt
python_mathematics_exercises_generator-0.0.1.dist-info/top_level.txt
python_mathematics_exercises_generator-0.0.1.dist-info/RECORD
