Metadata-Version: 2.1
Name: python-mathematics-exercises-generator
Version: 0.0.1
Summary: Add a short description here!
Home-page: https://github.com/iacchus/python-math-exercises-generator
Author: Iacchus Mercurius
Author-email: kassivs+git@gmail.com
License: AGPL-3.0-only
Project-URL: Documentation, https://github.com/iacchus/python-math-exercises-generator
Project-URL: Source, https://github.com/iacchus/python-math-exercises-generator
Project-URL: Tracker, https://github.com/pyscaffold/pyscaffold/issues
Platform: any
Classifier: Development Status :: 4 - Beta
Classifier: Intended Audience :: Developers
Classifier: Intended Audience :: Education
Classifier: License :: OSI Approved :: GNU Affero General Public License v3
Classifier: Programming Language :: Python
Classifier: Programming Language :: Python :: 3.10
Requires-Python: >=3.10
License-File: LICENSE.txt
Requires-Dist: click
Requires-Dist: sympy
Requires-Dist: toml
Requires-Dist: importlib-metadata ; python_version < "3.8"
Provides-Extra: testing
Requires-Dist: setuptools ; extra == 'testing'
Requires-Dist: pytest ; extra == 'testing'
Requires-Dist: pytest-cov ; extra == 'testing'
